[
    {
        "created_at": "2025-05-02T10:59:10.803705",
        "description": "222",
        "lat": 5.073415931515608,
        "lng": -75.50010681152345,
        "name": "Yo",
        "type": "interest"
    },
    {
        "created_at": "2025-05-02T10:59:11.031672",
        "description": "aa",
        "lat": 5.0742730006243075,
        "lng": -75.49113750457764,
        "name": "P1",
        "risk": 3,
        "type": "control"
    },
    {
        "created_at": "2025-05-02T13:31:30.905079",
        "description": "asas",
        "lat": 5.069699038953598,
        "lng": -75.51199436187746,
        "name": "P3",
        "risk": 5,
        "type": "control"
    },
    {
        "created_at": "2025-05-02T13:31:31.172955",
        "description": "asas",
        "lat": 5.063201392856124,
        "lng": -75.50933361053468,
        "name": "asas",
        "risk": 4,
        "type": "control"
    },
    {
        "created_at": "2025-05-02T13:31:31.225598",
        "description": "dfdf",
        "lat": 5.0620044509252144,
        "lng": -75.50366878509521,
        "name": "dfdf",
        "risk": 3,
        "type": "control"
    },
    {
        "created_at": "2025-05-02T13:31:31.820103",
        "description": "asas",
        "lat": 5.065424279135466,
        "lng": -75.49693107604982,
        "name": "PI2",
        "type": "interest"
    },
    {
        "created_at": "2025-05-02T13:31:31.877296",
        "description": "asas",
        "lat": 5.0685876041218085,
        "lng": -75.49118041992189,
        "name": "P2",
        "risk": 4,
        "type": "control"
    },
    {
        "lat": 5.062192058737969,
        "lng": -75.49551486968996,
        "name": "aa",
        "description": "a",
        "type": "control",
        "risk": 1,
        "created_at": "2025-05-02T19:37:36.655693"
    }
]